junior_ds/__init__.py
junior_ds/eda.py
junior_ds/missing_data_analysis.py
junior_ds/missing_data_imputation.py
junior_ds-3.2.dist-info/METADATA
junior_ds-3.2.dist-info/WHEEL
junior_ds-3.2.dist-info/top_level.txt
junior_ds-3.2.dist-info/RECORD
