Metadata-Version: 2.1
Name: junior-ds
Version: 3.2
Summary: This package is like having a junior Data Scientist working for you. So that you can delegate a lot of work and you focus on bringing insights. Techniques for making machine learning easy
Home-page: UNKNOWN
Author: Samarth Agrawal
Author-email: samarth.agrawal.86@gmail.com
License: UNKNOWN
Platform: UNKNOWN
Requires-Python: >=3.6
